pfio/__init__.py
pfio/_profiler.py
pfio/version.py
pfio/cache/__init__.py
pfio/cache/file_cache.py
pfio/cache/http_cache.py
pfio/cache/mmap_file_cache.py
pfio/cache/multiprocess_file_cache.py
pfio/cache/naive.py
pfio/testing/__init__.py
pfio/v2/__init__.py
pfio/v2/config.py
pfio/v2/fs.py
pfio/v2/hdfs.py
pfio/v2/http_cache.py
pfio/v2/local.py
pfio/v2/pathlib.py
pfio/v2/s3.py
pfio/v2/zip.py
pfio-2.9.0.dist-info/LICENSE
pfio-2.9.0.dist-info/METADATA
pfio-2.9.0.dist-info/WHEEL
pfio-2.9.0.dist-info/top_level.txt
pfio-2.9.0.dist-info/RECORD
