Metadata-Version: 2.1
Name: pfio
Version: 2.9.0
Summary: PFN IO library
Home-page: http://github.com/pfnet/pfio
Author: Tianqi Xu, Kota Uenishi
Author-email: tianqi@preferred.jp, kota@preferred.jp
Keywords: filesystem hdfs chainer development
Classifier: Development Status :: 3 - Alpha
Classifier: Intended Audience :: Developers
Classifier: License :: OSI Approved :: MIT License
Classifier: Operating System :: POSIX
Classifier: Operating System :: POSIX :: Linux
Classifier: Programming Language :: Python :: 3.9
Classifier: Programming Language :: Python :: 3.10
Classifier: Programming Language :: Python :: 3.11
Classifier: Programming Language :: Python :: 3.12
Classifier: Programming Language :: Python :: 3.13
Classifier: Topic :: System :: Filesystems
License-File: LICENSE
Requires-Dist: boto3
Requires-Dist: deprecation
Requires-Dist: urllib3
Provides-Extra: bench
Requires-Dist: numpy >=1.19.5 ; extra == 'bench'
Requires-Dist: torch >=1.9.0 ; extra == 'bench'
Requires-Dist: Pillow <=8.2.0 ; extra == 'bench'
Provides-Extra: doc
Requires-Dist: sphinx ; extra == 'doc'
Requires-Dist: sphinx-rtd-theme ; extra == 'doc'
Provides-Extra: hdfs
Requires-Dist: pyarrow >=6.0.0 ; extra == 'hdfs'
Provides-Extra: test
Requires-Dist: pytest ; extra == 'test'
Requires-Dist: flake8 ; extra == 'test'
Requires-Dist: autopep8 ; extra == 'test'
Requires-Dist: parameterized ; extra == 'test'
Requires-Dist: isort ; extra == 'test'
Requires-Dist: moto[server] >=5.0.0 ; extra == 'test'
Requires-Dist: numpy ; extra == 'test'
Requires-Dist: mypy ; extra == 'test'
Provides-Extra: trace
Requires-Dist: pytorch-pfn-extras ; extra == 'trace'
